easygui/__init__.py
easygui/easygui.py
easygui_wrap-1.0.8.dist-info/METADATA
easygui_wrap-1.0.8.dist-info/WHEEL
easygui_wrap-1.0.8.dist-info/top_level.txt
easygui_wrap-1.0.8.dist-info/RECORD
