Metadata-Version: 2.4
Name: easygui_wrap
Version: 1.0.8
Summary: A beginner-friendly, stylish GUI wrapper for Python using DearPyGui.
Home-page: https://github.com/thesmal
Author: Zaik
Author-email: stickma6@gmail.com
Keywords: gui easygui_wrap dearpygui python
Classifier: Development Status :: 5 - Production/Stable
Classifier: Intended Audience :: Developers
Classifier: Topic :: Software Development :: User Interfaces
Classifier: License :: OSI Approved :: MIT License
Classifier: Programming Language :: Python :: 3
Requires-Python: >=3.8
Requires-Dist: dearpygui>=2.0.0
Dynamic: author
Dynamic: author-email
Dynamic: classifier
Dynamic: description
Dynamic: description-content-type
Dynamic: home-page
Dynamic: keywords
Dynamic: requires-dist
Dynamic: requires-python
Dynamic: summary
